{
  "Align": "textAlign",
  "Anchor": "pvjson:delete",
  "BoardHeight": "height",
  "BoardWidth": "width",
  "CenterX": "x",
  "CenterY": "y",
  "Comment": "comments",
  "ConnectorType": "drawAs",
  "Database": "dbName",
  "FillColor": "backgroundColor",
  "FontName": "fontFamily",
  "Graphics": "pvjson:lift",
  "GraphId": "id",
  "GraphRef": "isAttachedTo",
  "ID": "dbId",
  "LineStyle": "strokeDasharray",
  "LineThickness": "borderWidth",
  "org.pathvisio.CellularComponentProperty": "cellularComponent",
  "org.pathvisio.DoubleLineProperty": "lineStyle",
  "Point": "points",
  "Shape": "drawAs",
  "ShapeType": "drawAs",
  "TextLabel": "displayName",
  "Version": "dataSourceVersion",
  "Valign": "verticalAlign",
  "Xref": "pvjson:lift",
  "ZOrder": "zIndex"
}
